{"children":[{"children":[],"uri":"https://www.notion.so/c7f4cc8be1be4fb195d98da412bd217a","type":"breadcrumb","createdTime":1573989039598,"lastEditedTime":1573989039598},{"children":[],"uri":"https://www.notion.so/a48bf3da79304cd185fe7e98797abc72","type":"text","createdTime":1587516420000,"lastEditedTime":1587516420000,"title":[]},{"children":[],"uri":"https://www.notion.so/4aceab297f4f4f41b1d6ddfd5f5e312f","type":"text","color":"gray","createdTime":1573989039598,"lastEditedTime":1587516480000,"title":[["如果你有時間寫一篇部落格文章，主題會關於什麼？"]]},{"children":[{"children":[],"uri":"https://www.notion.so/92d32e531ab74a6f84a14b974d9c24fc","type":"text","createdTime":1573989039600,"lastEditedTime":1573989039600,"title":[["To make hard questions easier to ask you can preface with one of these two:"]]},{"children":[],"uri":"https://www.notion.so/d7e2c13997a7414f94f5507ef3f0920c","type":"bulleted_list","createdTime":1573989039600,"lastEditedTime":1573989039600,"title":[["Can I ask you a personal question?"]]},{"children":[],"uri":"https://www.notion.so/ce240a0618b747939bb6c112f99e2929","type":"bulleted_list","createdTime":1573989039600,"lastEditedTime":1573989039600,"title":[["I learned a really great question to ask people today, but it’s a really hard question to ask. They'll ask, what’s the question?"]]},{"children":[],"uri":"https://www.notion.so/83475a5756b1458399318a508cce05b4","type":"text","createdTime":1573989039600,"lastEditedTime":1573989039600,"title":[["Be okay with the silence as the person thinks of their answer."]]},{"children":[],"uri":"https://www.notion.so/9706dba126744ab382de4f7d20a5c454","type":"text","createdTime":1573989039600,"lastEditedTime":1573989039600,"title":[["The energy you give off as you are asking is important. Show that you are calm, friendly, and very genuinely interested in what the person has to say."]]},{"children":[],"uri":"https://www.notion.so/cb22c870167447a6aacb2e320bac0e75","type":"text","createdTime":1573989039600,"lastEditedTime":1573989039600,"title":[]},{"children":[],"uri":"https://www.notion.so/41f8c6bc687e4e2e95d00e0f629e3ffc","type":"text","createdTime":1573989039600,"lastEditedTime":1573989039600,"title":[["When talking with someone and want to move the conversation past small talk quickly, I’ll often ask them if they want to play The Question Game. The only rule is that we ask questions back and forth and take turns answering. They’ll start with safe questions. You start with medium questions, but escalate pretty quickly. As soon as you both answer one high vulnerability question, your relationship instantly goes to a whole new level."]]},{"children":[],"uri":"https://www.notion.so/e6f8d9e6299f42fe9d05a892e16f779d","type":"text","createdTime":1573989039600,"lastEditedTime":1573989039600,"title":[]},{"children":[],"uri":"https://www.notion.so/00e75e2195d441b3b778d35566157179","type":"text","createdTime":1573989039600,"lastEditedTime":1573989039600,"title":[]}],"uri":"https://www.notion.so/f7b9d1d1cafe482a9da42a53f8178b81","type":"toggle","createdTime":1573989039598,"lastEditedTime":1573989039598,"title":[["Some Tips"]]},{"children":[{"children":[],"uri":"https://www.notion.so/dcfdfcaa027b4b5296a282740629bd79","type":"heading","createdTime":1573989039600,"lastEditedTime":1573989039600,"title":[["“A good question is like the one Albert Einstein asked himself as a small boy — ‘What would you see if you were traveling on a beam of light?’ That question launched the theory of relativity, E=MC2, and the atomic age’.",[["i",null]]]],"depth":1},{"children":[],"uri":"https://www.notion.so/d57ebac1c74a45d491048972af430619","type":"heading","createdTime":1573989039600,"lastEditedTime":1573989039600,"title":[["A good question question is not concerned with a correct answer.",[["i",null]]]],"depth":1},{"children":[],"uri":"https://www.notion.so/5d8b43e15589459fb0a39ba8482e5cda","type":"heading","createdTime":1573989039600,"lastEditedTime":1573989039600,"title":[["A good question cannot be answered immediately.",[["i",null]]]],"depth":1},{"children":[],"uri":"https://www.notion.so/c0a2eb3c87be46da8ba646d85b7acfb3","type":"heading","createdTime":1573989039600,"lastEditedTime":1573989039600,"title":[["A good question challenges existing answers.",[["i",null]]]],"depth":1},{"children":[],"uri":"https://www.notion.so/46d3b5a9401242df88a6503391266710","type":"heading","createdTime":1573989039600,"lastEditedTime":1573989039600,"title":[["A good question creates new territory of thinking.",[["i",null]]]],"depth":1},{"children":[],"uri":"https://www.notion.so/0655232179344a4eb972959aec2ec8bd","type":"heading","createdTime":1573989039600,"lastEditedTime":1573989039600,"title":[["A good question is one that generates many other good questions.",[["i",null]]]],"depth":1},{"children":[],"uri":"https://www.notion.so/b3c0dd7a7ea54d9da896b3789e4d687c","type":"heading","createdTime":1573989039600,"lastEditedTime":1573989039600,"title":[["A good question may be the last job a machine will learn to do.",[["i",null]]]],"depth":1},{"children":[],"uri":"https://www.notion.so/f5db478e4847483eba3b259c06b357fb","type":"heading","createdTime":1573989039600,"lastEditedTime":1573989039600,"title":[["A good question is what humans are for.”",[["i",null]]]],"depth":1}],"uri":"https://www.notion.so/f431bb45645140259d1bced804f23339","type":"toggle","createdTime":1573989039598,"lastEditedTime":1573989039598,"title":[["What makes a good question?"]]},{"children":[],"uri":"https://www.notion.so/b7da3b3a0a6f456d8b8106bdd160c38f","type":"text","createdTime":1573989039598,"lastEditedTime":1573989039598,"title":[]},{"children":[],"uri":"https://www.notion.so/5551f1e66eea4d5a9065d981304f32fa","type":"text","color":"orange","createdTime":1573989039598,"lastEditedTime":1573989039598,"title":[["Table of Contents",[["b",null]]]]},{"children":[],"uri":"https://www.notion.so/c7c3eeda90e5464eb424d2e5f44d5e07","type":"table_of_contents","color":"orange","createdTime":1573989039598,"lastEditedTime":1573989039598},{"children":[],"uri":"https://www.notion.so/9d56d2c503874b7bbcbd5ebe8aa1d180","type":"heading","createdTime":1573989039598,"lastEditedTime":1573989039598,"title":[["List"]],"depth":2},{"children":[],"uri":"https://www.notion.so/13731658d57e42b1908473c20a6fb71a","type":"text","createdTime":1573989039598,"lastEditedTime":1573989039598,"title":[["Why?"]]},{"children":[],"uri":"https://www.notion.so/8aa322eb801a48819f3ac24d4886c49b","type":"text","createdTime":1573989039598,"lastEditedTime":1573989039598,"title":[["What is an important truth (or something you believe) very few people agree with you on?"]]},{"children":[],"uri":"https://www.notion.so/77cd93567fcf46a7870608ef05d388ab","type":"text","createdTime":1573989039598,"lastEditedTime":1573989039598,"title":[["What is something you want to do that very few people also want to do? Like less than 1 or 2 of your 20 closest friends. "]]},{"children":[],"uri":"https://www.notion.so/88ff149ff24d4f8bab165a222d42ff49","type":"text","createdTime":1573989039598,"lastEditedTime":1573989039598,"title":[["Do you have any unusual but powerful habits?"]]},{"children":[],"uri":"https://www.notion.so/61d336a6cf6643b5a98bd87b4507322d","type":"text","createdTime":1573989039598,"lastEditedTime":1573989039598,"title":[["If you could write something in a banner that a huge amount of people would see, what would it be?"]]},{"children":[],"uri":"https://www.notion.so/759259bc72d94c45b296eec0c53e38a7","type":"text","createdTime":1573989039598,"lastEditedTime":1573989039598,"title":[["What should humanity strive for?"]]},{"children":[],"uri":"https://www.notion.so/68dd2b153cbb448582cab799d920b755","type":"text","createdTime":1573989039598,"lastEditedTime":1574955660000,"title":[["What systems do you use to navigate life? Which systems have given you the most leverage?",[["b",null]]]]},{"children":[],"uri":"https://www.notion.so/c8519cf7df9e437c912fb00d3c78fb98","type":"text","createdTime":1573989039598,"lastEditedTime":1573989039598,"title":[["What are your top 3 goals in life?"]]},{"children":[],"uri":"https://www.notion.so/a7043955f8f3468f866b9e123560fee5","type":"text","createdTime":1573989039598,"lastEditedTime":1574955600000,"title":[["What is something you believed in that you recently had to re-think?",[["b",null]]]]},{"children":[],"uri":"https://www.notion.so/ba993acc302a4ed788826635121dda82","type":"text","createdTime":1573989039598,"lastEditedTime":1573989039598,"title":[["What are you passionate about?"]]},{"children":[],"uri":"https://www.notion.so/ee666674fec146aaae52c460e1e4f041","type":"text","createdTime":1573989039598,"lastEditedTime":1573989039598,"title":[["What are you willing to struggle for?"]]},{"children":[],"uri":"https://www.notion.so/a12736c67a9a46a09d056ad7b7e3033d","type":"text","createdTime":1573989039598,"lastEditedTime":1573989039598,"title":[["What would you attempt to do if you knew you could not fail?"]]},{"children":[],"uri":"https://www.notion.so/3074adee697a43cba697fd69c72cc2d3","type":"text","createdTime":1573989039598,"lastEditedTime":1573989039598,"title":[["What's the best thing you could be working on, and why aren't you?"]]},{"children":[],"uri":"https://www.notion.so/33a564a86b1c4976acc8a804dfb795ee","type":"text","createdTime":1573989039598,"lastEditedTime":1573989039598,"title":[["What is the top idea on your mind?"]]},{"children":[],"uri":"https://www.notion.so/291994596c1545e1b9229e4b2f9da677","type":"text","createdTime":1573989039598,"lastEditedTime":1573989039598,"title":[["Do you have life principles? What are they?"]]},{"children":[],"uri":"https://www.notion.so/a59774c9ae6f409d810113ebb02646cb","type":"text","createdTime":1573989039598,"lastEditedTime":1573989039598,"title":[["What are your favorite life lessons?"]]},{"children":[],"uri":"https://www.notion.so/0fa5775756f44f9a957fe70576f20229","type":"text","createdTime":1573989039598,"lastEditedTime":1573989039598,"title":[["Anthropological questions: how has psychology influenced this field or what are the psychological repercussions of a certain event?"]]},{"children":[],"uri":"https://www.notion.so/b90d8a0ca2bd4493bb16ad15a45753fb","type":"text","createdTime":1573989039598,"lastEditedTime":1573989039598,"title":[["What is your favorite thing you learned this year?"]]},{"children":[],"uri":"https://www.notion.so/a43648d421d94f3bad556c55a933a725","type":"text","createdTime":1573989039598,"lastEditedTime":1573989039598,"title":[["What are your favorite mental models to navigate life? Most useful Mental models for your specific industry?"]]},{"children":[],"uri":"https://www.notion.so/0800ae6ac3884e1ead24a77d07bfad3f","type":"text","createdTime":1573989039598,"lastEditedTime":1573989039598,"title":[["What would you say, about your perspective in particular, has changed the most from the age of 21? Or whatever age"]]},{"children":[],"uri":"https://www.notion.so/25487aa652c24d098fd4712fde2bbd2c","type":"text","createdTime":1573989039598,"lastEditedTime":1573989039598,"title":[["What are your top 3 favorite questions?"]]},{"children":[],"uri":"https://www.notion.so/2042b8423b8e4511b490e988b23c1878","type":"text","createdTime":1573989039598,"lastEditedTime":1573989039598,"title":[["What's the best lesson your father ever taught you? Best lesson your mother ever taught you?"]]},{"children":[],"uri":"https://www.notion.so/ef2fdc684b76497f9ebf5a3384944f23","type":"text","createdTime":1573989039598,"lastEditedTime":1574955720000,"title":[["What are some of the choices you've made that made you who you are?",[["b",null]]]]},{"children":[],"uri":"https://www.notion.so/57afd5d27ed346cab0fb8fafb8158b87","type":"text","createdTime":1573989039598,"lastEditedTime":1574955720000,"title":[["Have you ever been in love?",[["b",null]]]]},{"children":[],"uri":"https://www.notion.so/db98f16c2f384027a380ad927cece665","type":"text","createdTime":1573989039598,"lastEditedTime":1573989039598,"title":[["If your knowledge was reset to zero, which books would you find it essential to read first?"]]},{"children":[],"uri":"https://www.notion.so/e2b2a3fb8ff443d4b20b4b86b16c7170","type":"text","createdTime":1573989039598,"lastEditedTime":1573989039598,"title":[["If you were 20 years old, what would you tell yourself?"]]},{"children":[],"uri":"https://www.notion.so/1fa39cced1f9478bb57f6b034ae2a2f1","type":"text","createdTime":1573989039598,"lastEditedTime":1573989039598,"title":[["What would you tell yourself right now?"]]},{"children":[],"uri":"https://www.notion.so/f71caeb4e43943128bce59628b25010a","type":"text","createdTime":1573989039598,"lastEditedTime":1573989039598,"title":[["How would you want to be remembered? Do you want to be remembered? By whom? "]]},{"children":[],"uri":"https://www.notion.so/eb6896748e4842b393e46ffc689a250a","type":"text","createdTime":1573989039598,"lastEditedTime":1573989039598,"title":[["What would you like your obituary to say?"]]},{"children":[],"uri":"https://www.notion.so/50436a6d2cb340c2bff19f651c77b23a","type":"text","createdTime":1573989039598,"lastEditedTime":1573989039598,"title":[["What’s the most useful piece of advice you’ve ever received?"]]},{"children":[],"uri":"https://www.notion.so/824a410c8a1a40f796ac3a6b3c7181d9","type":"text","createdTime":1573989039598,"lastEditedTime":1573989039598,"title":[["To someone really awoken: how could I increase my consciousness level?"]]},{"children":[],"uri":"https://www.notion.so/4683f7eeed584cdf8362181ab308221c","type":"text","createdTime":1573989039598,"lastEditedTime":1573989039598,"title":[["What do you want the most out of life?"]]},{"children":[],"uri":"https://www.notion.so/79874c5ee0534d53b3321ab1b019ba81","type":"text","createdTime":1573989039598,"lastEditedTime":1573989039598,"title":[["What means the most to you in life (ONLY ONE) and why?"]]},{"children":[],"uri":"https://www.notion.so/725fad1d96f946fdb7a0b66a0bf77756","type":"text","createdTime":1573989039598,"lastEditedTime":1573989039598,"title":[["What's your greatest struggle and how did you overcome it?"]]},{"children":[],"uri":"https://www.notion.so/45e5b6aee32341f786e6495c59412e85","type":"text","createdTime":1573989039598,"lastEditedTime":1573989039598,"title":[["What do you regret?"]]},{"children":[],"uri":"https://www.notion.so/13179d3a67b84a7c869597c23cd3c6e9","type":"text","createdTime":1573989039598,"lastEditedTime":1573989039598,"title":[["What books have you gifted the most?"]]},{"children":[],"uri":"https://www.notion.so/dd211adbe1b34fff844eeb9a31d32546","type":"text","createdTime":1573989039598,"lastEditedTime":1573989039598,"title":[["What are your favorite books?"]]},{"children":[],"uri":"https://www.notion.so/c6cdc62b4f6c43d5b3565fe5a13656d8","type":"text","createdTime":1573989039598,"lastEditedTime":1573989039598,"title":[["What is some advice you're happy you ignored?"]]},{"children":[],"uri":"https://www.notion.so/af3bc9514bc846c2852334a584de7ebf","type":"text","createdTime":1573989039598,"lastEditedTime":1573989039598,"title":[["What matters?"]]},{"children":[],"uri":"https://www.notion.so/3fc8845b9b324644b89f5d785173b8a5","type":"text","createdTime":1573989039598,"lastEditedTime":1573989039598,"title":[["What was a moment you couldn’t stop laughing?"]]},{"children":[],"uri":"https://www.notion.so/8d10958a72bd471085170050df99dc86","type":"text","createdTime":1573989039598,"lastEditedTime":1573989039598,"title":[["What has been the most pivotal moment of your life so far?"]]},{"children":[],"uri":"https://www.notion.so/676cf8d915904e22ab25b520b2a08a42","type":"text","createdTime":1573989039598,"lastEditedTime":1573989039598,"title":[["How did you meet your girlfriend/boyfriend? After they answer, Can you tell me about them?"]]},{"children":[],"uri":"https://www.notion.so/0ea3eca2066d474d86e92b9eba4684f0","type":"text","createdTime":1573989039598,"lastEditedTime":1573989039598,"title":[["What were you surprised to learn about [Name of person]?"]]},{"children":[],"uri":"https://www.notion.so/737fcd224bd84d6ea796fbc6f738e629","type":"text","createdTime":1573989039598,"lastEditedTime":1573989039598,"title":[["What is your favorite thing about [Name of person]?"]]},{"children":[],"uri":"https://www.notion.so/d0b4ae082214447abd96ed524358c905","type":"text","createdTime":1573989039598,"lastEditedTime":1573989039598,"title":[["Can you tell me a story/specific moment about a time when ____?"]]},{"children":[],"uri":"https://www.notion.so/7a51214c95764d11a8ff7cc74b16bb06","type":"text","createdTime":1573989039598,"lastEditedTime":1573989039598,"title":[["What is your greatest struggle right now?"]]},{"children":[],"uri":"https://www.notion.so/1c013818478d49f0b028b730a9fdad9e","type":"text","createdTime":1573989039598,"lastEditedTime":1573989039598,"title":[["What are you most afraid of right now?"]]},{"children":[],"uri":"https://www.notion.so/c0adb1bf7934410c9144605cc74ff949","type":"text","createdTime":1573989039598,"lastEditedTime":1573989039598,"title":[["What was the happiest moment of your life?"]]},{"children":[],"uri":"https://www.notion.so/a94cca6d5edf4c59bd1fc83e62ec1f9d","type":"text","createdTime":1573989039598,"lastEditedTime":1573989039598,"title":[["When in your life did you feel the most guilty?"]]},{"children":[],"uri":"https://www.notion.so/2c1d0dde731c46edb7093c147e4c0a93","type":"text","createdTime":1573989039598,"lastEditedTime":1573989039598,"title":[["When were you most afraid?"]]},{"children":[],"uri":"https://www.notion.so/d82848406a5c40c2b9079ae0383e0056","type":"text","createdTime":1573989039598,"lastEditedTime":1573989039598,"title":[["Do you remember the saddest moment in your life?"]]},{"children":[],"uri":"https://www.notion.so/01063876541f47c4a6e19de033b39426","type":"text","createdTime":1573989039598,"lastEditedTime":1573989039598,"title":[["When were you most angry?"]]},{"children":[],"uri":"https://www.notion.so/a56309d1fd4642ac98d7e36843c62d78","type":"text","createdTime":1573989039598,"lastEditedTime":1573989039598,"title":[["When do you feel angry?"]]},{"children":[],"uri":"https://www.notion.so/20d285634b604ce8935d57d389751811","type":"text","createdTime":1573989039598,"lastEditedTime":1573989039598,"title":[["What would you do if you had an extra hour every day? "]]},{"children":[],"uri":"https://www.notion.so/85a6986885ef4f54bd3b67bafa7a89f4","type":"text","createdTime":1573989039598,"lastEditedTime":1573989039598,"title":[["What would you do if you had an extra 5 hours per week? "]]},{"children":[],"uri":"https://www.notion.so/9038880327064017b9806b177b0ed71e","type":"text","createdTime":1573989039598,"lastEditedTime":1573989039598,"title":[["How do you like spending your free time? how do you spend your free time? "]]},{"children":[],"uri":"https://www.notion.so/341b78a92031402e976e0064c2b08167","type":"text","createdTime":1573989039598,"lastEditedTime":1573989039598,"title":[["What do you do when you have time for yourself? "]]},{"children":[],"uri":"https://www.notion.so/236ffd8048e04086b60cce2e610d9bc7","type":"text","createdTime":1573989039598,"lastEditedTime":1573989039598,"title":[["What are your favorite topics? "]]},{"children":[],"uri":"https://www.notion.so/fdf32f258a884029a26a0fde5c821ecd","type":"text","createdTime":1573989039598,"lastEditedTime":1573989039598,"title":[]},{"children":[],"uri":"https://www.notion.so/1141d55e024f40128e4a0310ecef2db3","type":"text","createdTime":1573989039598,"lastEditedTime":1573989039598,"title":[]},{"children":[],"uri":"https://www.notion.so/df6f9585ce924262867e4c406ea19009","type":"text","createdTime":1573989039598,"lastEditedTime":1573989039598,"title":[]},{"children":[],"uri":"https://www.notion.so/333c9f8f937c4f71bacbd0c02114d308","type":"text","createdTime":1573989039598,"lastEditedTime":1573989039598,"title":[["What would this look like if it were easy?"]]},{"children":[],"uri":"https://www.notion.so/e69eb2a211014c0eab2f73e9f6334a64","type":"text","createdTime":1573989039599,"lastEditedTime":1573989039599,"title":[["For something you think you can only achieve in 2-5-10 or more years: if I only had 6 months to achieve this, what would I have to do?"]]},{"children":[],"uri":"https://www.notion.so/1f1e1b36002643bcbdadc342c4dbefcd","type":"text","createdTime":1573989039599,"lastEditedTime":1573989039599,"title":[]},{"children":[],"uri":"https://www.notion.so/518e990afe7642bd98a3e9a194297729","type":"text","createdTime":1573989039599,"lastEditedTime":1573989039599,"title":[]},{"children":[{"children":[],"uri":"https://www.notion.so/c63f7eab9ba44151af5f1a960e020f46","type":"text","createdTime":1573989039600,"lastEditedTime":1573989039600,"title":[["Is it true? Can you be absolutely sure it's true? How do you react when you think that thought? Who would you be without that thought?"]]}],"uri":"https://www.notion.so/3bdde85058824ee1a60a8b7173341c33","type":"toggle","createdTime":1573989039599,"lastEditedTime":1573989039599,"title":[["From Loving What Is: Four Questions that can Change Your Life"]]},{"children":[],"uri":"https://www.notion.so/fec65a12d2bb4a07b2701370978c2a57","type":"text","createdTime":1573989039599,"lastEditedTime":1573989039599,"title":[]},{"children":[],"uri":"https://www.notion.so/14a43d59c50d4b52b7c9371f0b47ec4c","type":"text","createdTime":1573989039599,"lastEditedTime":1573989039599,"title":[["What’s a life hack you do that very few people know about? "]]},{"children":[],"uri":"https://www.notion.so/9945dd32260a4afd8e3f7e97e5f83b0e","type":"text","createdTime":1573989039599,"lastEditedTime":1573989039599,"title":[["What is something controversial now that you think won’t be in a couple of years? "]]},{"children":[],"uri":"https://www.notion.so/c213ad76bdee44479ae37f43c529d996","type":"text","createdTime":1573989039599,"lastEditedTime":1573989039599,"title":[["What are two to three people you think will be super impactful that aren’t yet? "]]},{"children":[],"uri":"https://www.notion.so/cbf8e8ae54114c96b60bd27ccc178690","type":"text","createdTime":1573989039599,"lastEditedTime":1573989039599,"title":[["What do you think is the thing holding people back the most? "]]},{"children":[],"uri":"https://www.notion.so/127399aa33364bf984ce652a7dedb42c","type":"text","createdTime":1573989039599,"lastEditedTime":1573989039599,"title":[["What is the kindest thing someone has done to you? "]]},{"children":[],"uri":"https://www.notion.so/3e749fa30d3741c786b2f79f1fd61769","type":"text","createdTime":1573989039599,"lastEditedTime":1573989039599,"title":[["What’s the smallest habit you have that makes the biggest difference? "]]},{"children":[],"uri":"https://www.notion.so/77a9e4ce85f845cea3fe17ea9504ea53","type":"text","createdTime":1573989039599,"lastEditedTime":1573989039599,"title":[]},{"children":[],"uri":"https://www.notion.so/a99e0aba1a4c4443b706fcfc036c0fe3","type":"text","createdTime":1573989039599,"lastEditedTime":1573989039599,"title":[]},{"children":[],"uri":"https://www.notion.so/834abf3d157e4732a6a7eb3d4b59af1b","type":"text","createdTime":1573989039599,"lastEditedTime":1573989039599,"title":[["For something challenging/a hardship: How can this be seen as a gift? "]]},{"children":[],"uri":"https://www.notion.so/442c8990a3314148abed068efe35ca95","type":"text","createdTime":1573989039599,"lastEditedTime":1573989039599,"title":[]},{"children":[],"uri":"https://www.notion.so/a3c72cc761de49b1a3a2379e800b315f","type":"text","createdTime":1573989039599,"lastEditedTime":1573989039599,"title":[]},{"children":[],"uri":"https://www.notion.so/892844c179844f93b1bc7f1d8f30c8ce","type":"heading","createdTime":1573989039599,"lastEditedTime":1573989039599,"title":[["For famous, talented people in certain fields"]],"depth":1},{"children":[],"uri":"https://www.notion.so/5d97e8b96a764c768db428c63b96d30f","type":"text","createdTime":1573989039599,"lastEditedTime":1573989039599,"title":[["What are the three questions you get asked more often? What are your answers?"]]},{"children":[],"uri":"https://www.notion.so/7affd19d67384b4582fbfaa0e51b7cee","type":"text","createdTime":1573989039599,"lastEditedTime":1573989039599,"title":[["What question do you wish people asked you more?"]]},{"children":[],"uri":"https://www.notion.so/85cd0896b2dd45c69e134ebd293dc48b","type":"text","createdTime":1573989039599,"lastEditedTime":1573989039599,"title":[["What is the impact you want to have on the world?"]]},{"children":[],"uri":"https://www.notion.so/00c39aab58a04f478e7b2c877be018fb","type":"text","createdTime":1573989039599,"lastEditedTime":1573989039599,"title":[]},{"children":[],"uri":"https://www.notion.so/e478ede757f24d3e8a28cd6ef499d9d4","type":"text","createdTime":1573989039599,"lastEditedTime":1573989039599,"title":[["Some of my favorite for \"experts\":\nMost useful mental models for your specific industry?\nWhat is some advice you're happy you ignored?\nWhat question do you wish people asked you more?\nWhat do most people get wrong about X industry?\nIf you could write something in a banner that a huge amount of people would see, what would it be?"]]},{"children":[],"uri":"https://www.notion.so/834d32d557e945e9af7b247732484959","type":"heading","createdTime":1573989039599,"lastEditedTime":1573989039599,"title":[["Tempting Questions for Self"]],"depth":1},{"children":[],"uri":"https://www.notion.so/f8e69f254e8b406fbf19bef52be45b36","type":"text","createdTime":1573989039599,"lastEditedTime":1573989039599,"title":[["If I wasn’t thinking about this, would it still be a problem?”"]]},{"children":[],"uri":"https://www.notion.so/d28fe753dd9b43c486209ed2bf7b0b97","type":"text","createdTime":1573989039599,"lastEditedTime":1573989039599,"title":[["How often do you just complain when you should instead be setting an example?"]]},{"children":[],"uri":"https://www.notion.so/4c7abdb7f68345dbbcd43c6cb212055b","type":"text","createdTime":1573989039599,"lastEditedTime":1573989039599,"title":[["Is there anyone that's helped you along the way that you haven't thanked enough?"]]},{"children":[],"uri":"https://www.notion.so/762853ac88734375b3df42e47b01bac0","type":"text","createdTime":1573989039599,"lastEditedTime":1573989039599,"title":[["What would you do more of if you didn’t have to worry about being perfect at it?"]]},{"children":[],"uri":"https://www.notion.so/de6cbda56d4d4b1c9929e5c4d523825d","type":"text","createdTime":1573989039599,"lastEditedTime":1573989039599,"title":[["How many of your problems are due to you answering the wrong questions?"]]},{"children":[],"uri":"https://www.notion.so/3ff2143899c24543bc4c541c574faecc","type":"text","createdTime":1573989039599,"lastEditedTime":1573989039599,"title":[["What would you stop doing if you only had a year left to live? What would you start doing if you had 10,000 years to live?"]]},{"children":[],"uri":"https://www.notion.so/cccc04cdb8424e48839c63f9da6885d6","type":"text","createdTime":1573989039599,"lastEditedTime":1573989039599,"title":[]},{"children":[],"uri":"https://www.notion.so/b0bdfd7538724815aef837a6de7738c1","type":"text","createdTime":1573989039599,"lastEditedTime":1573989039599,"title":[["What is one thing you can remove from your life that would improve it?"]]},{"children":[],"uri":"https://www.notion.so/e8df29ec63fc4f889385155be7ec07bb","type":"text","createdTime":1573989039599,"lastEditedTime":1573989039599,"title":[["How many opinions do you accept simply because you fear saying “I don’t know”?"]]},{"children":[],"uri":"https://www.notion.so/29ee2e86dea640f69d2db5c3ad5b5806","type":"text","createdTime":1573989039599,"lastEditedTime":1573989039599,"title":[["What's something you used to know that would be useful to remember again?"]]},{"children":[],"uri":"https://www.notion.so/da68ce0fe0374d3996b5c7dda93953ae","type":"text","createdTime":1573989039599,"lastEditedTime":1573989039599,"title":[]},{"children":[],"uri":"https://www.notion.so/51b21ef2ccb54d0abdc504201fb63344","type":"bulleted_list","createdTime":1573989039599,"lastEditedTime":1573989039599,"title":[["‘What is the most capable version of me that I can imagine?’"]]},{"children":[],"uri":"https://www.notion.so/16469397e2f8409d963f6e3a444651f9","type":"bulleted_list","createdTime":1573989039599,"lastEditedTime":1573989039599,"title":[["‘What would I be like/spend my time doing if all my current major problems had been solved?’"]]},{"children":[],"uri":"https://www.notion.so/c8331ba1f26e4be699447e38a387dcb0","type":"bulleted_list","createdTime":1573989039599,"lastEditedTime":1573989039599,"title":[["‘What are the things I say I value but don’t act as if I value, and what would my life feel like if I actually acted as if I valued those things?’"]]},{"children":[],"uri":"https://www.notion.so/7871fe2e6aae4452a2b60022814757f8","type":"bulleted_list","createdTime":1573989039599,"lastEditedTime":1573989039599,"title":[["‘What am I afraid of doing, and what would my life be like if I wasn’t afraid of doing those things?’"]]},{"children":[],"uri":"https://www.notion.so/d43d7493fb184847893419c8c0e2e381","type":"text","createdTime":1573989039599,"lastEditedTime":1573989039599,"title":[]},{"children":[],"uri":"https://www.notion.so/08c1ffb0f82a4353bdbee89eb6fedc2d","type":"text","createdTime":1573989039599,"lastEditedTime":1573989039599,"title":[["How much of what you care about is based on wanting others to think you care?"]]},{"children":[],"uri":"https://www.notion.so/08a9c14fa18c42a6bd430f48ceb01ef9","type":"text","createdTime":1573989039599,"lastEditedTime":1573989039599,"title":[["If you were 90, how much would you pay to go back to relive the moments you’re living? "]]},{"children":[],"uri":"https://www.notion.so/8de334627e6140859b5bd5e15b5a408c","type":"text","createdTime":1573989039599,"lastEditedTime":1573989039599,"title":[]},{"children":[],"uri":"https://www.notion.so/db1b48214ff54dfd9390c4e50ef42817","type":"text","createdTime":1573989039599,"lastEditedTime":1573989039599,"title":[["What would you do if you had no responsibilities?"]]},{"children":[],"uri":"https://www.notion.so/181d129030484b7cabdcf4d754d9c1e1","type":"text","createdTime":1573989039599,"lastEditedTime":1573989039599,"title":[]},{"children":[],"uri":"https://www.notion.so/dd682db4ed2747b395be4f66013ad708","type":"bulleted_list","createdTime":1573989039599,"lastEditedTime":1573989039599,"title":[["Am I excited to be doing what I’m doing or am I in aimless motion?"]]},{"children":[],"uri":"https://www.notion.so/f1c8099824fa4c888772c2c590a6990a","type":"bulleted_list","createdTime":1573989039599,"lastEditedTime":1573989039599,"title":[["Are the trade-offs between work and my relationships [or my life buckets] well-balanced?"]]},{"children":[],"uri":"https://www.notion.so/a251a3aceca146ba8de25570f063c080","type":"bulleted_list","createdTime":1573989039599,"lastEditedTime":1573989039599,"title":[["How can I speed up the process from where I am to where I want to go?"]]},{"children":[],"uri":"https://www.notion.so/472144c3dced43b1b68b5785e59d7738","type":"bulleted_list","createdTime":1573989039599,"lastEditedTime":1573989039599,"title":[["What big opportunities am I not pursuing that I potentially could?"]]},{"children":[],"uri":"https://www.notion.so/43353e78458644f1a7ff764abb3273b2","type":"bulleted_list","createdTime":1573989039599,"lastEditedTime":1573989039599,"title":[["What’s a small thing that will produce a disproportionate impact?"]]},{"children":[],"uri":"https://www.notion.so/4c05e36c59e64b1fb80d6e529d703039","type":"bulleted_list","createdTime":1573989039599,"lastEditedTime":1573989039599,"title":[["What could probabilistically go wrong in the next 6 months of my life?"]]},{"children":[],"uri":"https://www.notion.so/c85bb89da70e48668bce2815b48dbf2b","type":"bulleted_list","createdTime":1573989039599,"lastEditedTime":1573989039599,"title":[["When I had the opportunity, did I choose courage over comfort?"]]},{"children":[],"uri":"https://www.notion.so/d71a75cdd16a402ebe038ffdacb6a398","type":"text","createdTime":1573989039599,"lastEditedTime":1573989039599,"title":[]},{"children":[],"uri":"https://www.notion.so/fdacb6c86f434619bf623d997590ac96","type":"text","createdTime":1573989039599,"lastEditedTime":1573989039599,"title":[["How long will you put off what you are capable of doing just to continue what you are comfortable doing?"]]},{"children":[],"uri":"https://www.notion.so/fa7043c4a72f402eafb7f6dac8830099","type":"text","createdTime":1575312501939,"lastEditedTime":1575312480000,"title":[["How long will you put off what you are capable of doing just to continue what you are comfortable doing?"]]},{"children":[],"uri":"https://www.notion.so/0c64ccc80c764517be2518fdba3f8a67","type":"text","createdTime":1573989039599,"lastEditedTime":1573989039599,"title":[]},{"children":[],"uri":"https://www.notion.so/24b2820e314c4b7f8aa1b2e9368cda5f","type":"heading","createdTime":1573989039599,"lastEditedTime":1573989039599,"title":[["Good questions to bring out your inner artist out:",[["b",null]]]],"depth":3},{"children":[],"uri":"https://www.notion.so/edbc7a0e6e1a4cad93a6c1faedef7481","type":"text","createdTime":1573989039599,"lastEditedTime":1573989039599,"title":[["What are 5 hobbies that sound fun?"]]},{"children":[],"uri":"https://www.notion.so/ef3cfcbb46b64f05a93d1f41483bf9ee","type":"text","createdTime":1573989039599,"lastEditedTime":1573989039599,"title":[["What are 5 things you personally wouldn’t do that sound fun?"]]},{"children":[],"uri":"https://www.notion.so/c239af3ac5974bc09d0bb342352aa198","type":"text","createdTime":1573989039599,"lastEditedTime":1573989039599,"title":[["What are 5 things you wish you enjoyed doing?"]]},{"children":[],"uri":"https://www.notion.so/5806d7bc0f0b4a0783c52dd91147295a","type":"text","createdTime":1573989039599,"lastEditedTime":1573989039599,"title":[["What are 5 things you want to try once?"]]},{"children":[],"uri":"https://www.notion.so/058a8511eb4a49b6babf0b6ea86c026a","type":"text","createdTime":1573989039599,"lastEditedTime":1573989039599,"title":[["If I were 20 and had money, list 5 adventures I would take"]]},{"children":[],"uri":"https://www.notion.so/cb17040c23694573894f3331daa99a42","type":"text","createdTime":1573989039599,"lastEditedTime":1573989039599,"title":[["65 and money: 5 postponed pleasures / adventures"]]},{"children":[],"uri":"https://www.notion.so/7aed62f9ff344870bcbeb3bf81173474","type":"text","createdTime":1573989039599,"lastEditedTime":1573989039599,"title":[["5 items I want to own but don’t"]]},{"children":[],"uri":"https://www.notion.so/c266cd89264c407283a304bb4041b34f","type":"heading","createdTime":1573989039599,"lastEditedTime":1573989039599,"title":[["Questions that Pull Out Interesting"]],"depth":1},{"children":[],"uri":"https://www.notion.so/5a249858c3e54fe5a1b4df08d362bab8","type":"text","createdTime":1573989039599,"lastEditedTime":1573989039599,"title":[["What is something you'd want to prove but can't?"]]},{"children":[],"uri":"https://www.notion.so/5b69107587af4ce292d36a9737c0a766","type":"text","createdTime":1573989039599,"lastEditedTime":1573989039599,"title":[["What is something you see most people believe but you think is wrong?"]]},{"children":[],"uri":"https://www.notion.so/8a921185328447f1af9db3565bfd9cbb","type":"text","createdTime":1573989039599,"lastEditedTime":1573989039599,"title":[["What is something you believe that very few people also believe?"]]},{"children":[],"uri":"https://www.notion.so/a76383f8386d4a858e902e26b58a8ddc","type":"text","createdTime":1573989039599,"lastEditedTime":1573989039599,"title":[["What's true but not obvious? As in, what's a robust heuristic not yet a cliche?"]]},{"children":[],"uri":"https://www.notion.so/4280eae7f4c74faaa0263f930b9ad5b2","type":"text","createdTime":1573989039599,"lastEditedTime":1573989039599,"title":[["What have been the 3 most pivotal moments in your life?"]]},{"children":[],"uri":"https://www.notion.so/2d0fff7be91149528503f67fb5224d94","type":"text","createdTime":1573989039599,"lastEditedTime":1573989039599,"title":[]},{"children":[],"uri":"https://www.notion.so/91e683117825453dbca56d29d65ec71a","type":"text","createdTime":1573989039599,"lastEditedTime":1573989039599,"title":[]},{"children":[],"uri":"https://www.notion.so/478a7f180db143df941b159f6b2b58a5","type":"page","createdTime":1573989039599,"lastEditedTime":1575311220000,"title":[["Questions for Junto Intro"]],"fullWidth":false,"coverPosition":1,"properties":{"title":[["Questions for Junto Intro"]]}},{"children":[],"uri":"https://www.notion.so/45564b5f362048e09bac608a368842d1","type":"text","createdTime":1573989039599,"lastEditedTime":1573989039599,"title":[]},{"children":[],"uri":"https://www.notion.so/3c00428018ae462f89d2ceb11e4467ee","type":"heading","createdTime":1573989039599,"lastEditedTime":1573989039599,"title":[["Questions for refining ideas"]],"depth":1},{"children":[],"uri":"https://www.notion.so/65d2ff19c82a42bf95cd176a3856dbca","type":"text","createdTime":1573989039599,"lastEditedTime":1573989039599,"title":[]},{"children":[],"uri":"https://www.notion.so/980192ef0dfc409ab889c812d14e20c5","type":"text","createdTime":1573989039599,"lastEditedTime":1573989039599,"title":[["But how do you combine the ideas? Are there specific processes you can use? How do you refine ideas? How do you assess ideas? "]]},{"children":[],"uri":"https://www.notion.so/b0c8e2ec90324c079619cea44db57edf","type":"text","createdTime":1573989039599,"lastEditedTime":1573989039599,"title":[]},{"children":[],"uri":"https://www.notion.so/0383f8e89910408991f26fc0fe9933a9","type":"text","createdTime":1573989039599,"lastEditedTime":1573989039599,"title":[["I like to ask questions to inspire new thoughts. Questions trigger answers. Questions can change the angle at which you’re looking at something — or they can direct your eyes to look at something new. "]]},{"children":[],"uri":"https://www.notion.so/0d7ae0eec3704deb99d60afa31a2a0d1","type":"text","createdTime":1573989039599,"lastEditedTime":1573989039599,"title":[]},{"children":[],"uri":"https://www.notion.so/9d66cc549ac74cae927d541e2504ddcf","type":"text","createdTime":1573989039599,"lastEditedTime":1573989039599,"title":[["Some examples I’ve found useful for refining, combining, and assessing ideas include: "]]},{"children":[],"uri":"https://www.notion.so/ad844db1a8b34b6ba90ed1c6696869c2","type":"text","createdTime":1573989039599,"lastEditedTime":1573989039599,"title":[["Under what circumstances does this apply?"]]},{"children":[],"uri":"https://www.notion.so/94cbebe4f0b5443b91590399c5432c01","type":"text","createdTime":1573989039599,"lastEditedTime":1573989039599,"title":[["(For hard, long term ideas): how can I do this in 6 months instead of 5 years? "]]},{"children":[],"uri":"https://www.notion.so/f08d720f267c44929660f2fd40bd0dd6","type":"text","createdTime":1573989039599,"lastEditedTime":1573989039599,"title":[["What is something you believe that very few people also believe? "]]},{"children":[],"uri":"https://www.notion.so/b83a8f06005b4902bef6cec4d967d070","type":"text","createdTime":1573989039599,"lastEditedTime":1573989039599,"title":[["What is something you want to do in your life that less than 2 of your 10 closest friends also want to do? "]]},{"children":[],"uri":"https://www.notion.so/23669ed9f53343b48be294f5d9d78d68","type":"text","createdTime":1573989039599,"lastEditedTime":1573989039599,"title":[["At the end of your life, as you look back, would you regret this? "]]},{"children":[],"uri":"https://www.notion.so/9ef60315e77a4a79867dfced4a11b367","type":"text","createdTime":1573989039599,"lastEditedTime":1573989039599,"title":[["What’s the worst thing that could happen? "]]},{"children":[],"uri":"https://www.notion.so/0db78931adf74048a956703aa457d516","type":"text","createdTime":1573989039599,"lastEditedTime":1573989039599,"title":[["What is the expected outcome? Weighted with probabilities and assessing the values."]]},{"children":[],"uri":"https://www.notion.so/add78c1def1345c0a87cadf4f1330bc7","type":"text","createdTime":1573989039599,"lastEditedTime":1573989039599,"title":[["How can you create a third option? "]]},{"children":[],"uri":"https://www.notion.so/0ff6f9ac042d42c5ae2c7a7ed1ea4e61","type":"text","createdTime":1573989039599,"lastEditedTime":1573989039599,"title":[["What would this look like in 5-10 years?"]]},{"children":[],"uri":"https://www.notion.so/06c5e04458af47058ee86871252a46b9","type":"text","createdTime":1573989039599,"lastEditedTime":1573989039599,"title":[["What will likely change in 10 years? "]]},{"children":[],"uri":"https://www.notion.so/590c33e523bf4486a2a9de0080749820","type":"text","createdTime":1573989039599,"lastEditedTime":1573989039599,"title":[["What will not change in 10 years? "]]},{"children":[],"uri":"https://www.notion.so/546ed91ca0ff44d7857ed0803da2b567","type":"text","createdTime":1573989039599,"lastEditedTime":1573989039599,"title":[["Why does this matter? Why do you want to do it? "]]},{"children":[],"uri":"https://www.notion.so/2c2a5a89509f4951b1ae887e9e1b5b82","type":"text","createdTime":1573989039599,"lastEditedTime":1573989039599,"title":[["Is there a harder way of doing it? Is there an easier way? Is there a faster or cheaper way?"]]},{"children":[],"uri":"https://www.notion.so/674a8b2a1b1b4fa5b4a7d125abd5653e","type":"text","createdTime":1573989039599,"lastEditedTime":1573989039599,"title":[["Is this in alignment with your values? With your life purpose? "]]},{"children":[],"uri":"https://www.notion.so/19c1d0285ebd401aba3be58a448a0e10","type":"text","createdTime":1573989039599,"lastEditedTime":1573989039599,"title":[["Are you thinking long term? "]]},{"children":[],"uri":"https://www.notion.so/b4553f3a1d2642e48c0f01fa4a6ddcd5","type":"text","createdTime":1573989039599,"lastEditedTime":1573989039599,"title":[["What is some possible emergent behavior that might arise? "]]},{"children":[],"uri":"https://www.notion.so/173a0d3de6234ca6913ae3653d2541ae","type":"text","createdTime":1573989039599,"lastEditedTime":1573989039599,"title":[["What are the psychological implications? Economical, brand, philosophical, moral implications."]]},{"children":[],"uri":"https://www.notion.so/008a8a9dadb04f99b749aa2cc32884d8","type":"text","createdTime":1573989039599,"lastEditedTime":1573989039599,"title":[["Have you taken enough time to think about this? "]]},{"children":[],"uri":"https://www.notion.so/177433b5bd9444fa936f629ef078043f","type":"text","createdTime":1573989039599,"lastEditedTime":1573989039599,"title":[["Do you even need more time? "]]},{"children":[],"uri":"https://www.notion.so/e743a00c8a584496b7b62a04ed07030b","type":"text","createdTime":1573989039599,"lastEditedTime":1573989039599,"title":[["What is something people would be scared of? "]]},{"children":[],"uri":"https://www.notion.so/57cec616d1d44b8b9fa0ce4b5e68e32c","type":"text","createdTime":1573989039599,"lastEditedTime":1573989039599,"title":[["How can you add an element of surprise / delight / elegance / legitimacy, etc. ? "]]},{"children":[],"uri":"https://www.notion.so/52d5c65d6cc747fa8956068a86519487","type":"text","createdTime":1573989039599,"lastEditedTime":1573989039599,"title":[["What feeling do you want to evoke? "]]},{"children":[],"uri":"https://www.notion.so/d32c6101c44b4172957f8f5e934e6bfe","type":"text","createdTime":1573989039599,"lastEditedTime":1573989039599,"title":[["What does this stand for? Does it represent something? "]]},{"children":[],"uri":"https://www.notion.so/8d30ab067e0149e18eac6a87208146d1","type":"text","createdTime":1573989039600,"lastEditedTime":1573989039600,"title":[["What are the second and third order implications?"]]},{"children":[],"uri":"https://www.notion.so/62c0bcc1b1c24f469b5706e7c29178df","type":"text","createdTime":1573989039600,"lastEditedTime":1573989039600,"title":[["How can this be improved? "]]},{"children":[],"uri":"https://www.notion.so/6f8da45916f4487385cd1c47528c80e9","type":"text","createdTime":1573989039600,"lastEditedTime":1573989039600,"title":[["Brainstorm what would be a six-star experience. A 7, 8, 9, 10, 11 star experience? Come up with something for each one."]]},{"children":[],"uri":"https://www.notion.so/7ef8b0ac72354c7392d699c41a6db3af","type":"text","createdTime":1573989039600,"lastEditedTime":1573989039600,"title":[["What can you compromise? What can’t be compromised?"]]},{"children":[],"uri":"https://www.notion.so/0ece15ca57ae4618a2884f88b1aabdf0","type":"text","createdTime":1573989039600,"lastEditedTime":1573989039600,"title":[["What are WOW features? What are absolutely essential features? What are nice to haves?"]]},{"children":[],"uri":"https://www.notion.so/073263aebf9a46078172de6d1fb3d45f","type":"text","createdTime":1573989039600,"lastEditedTime":1573989039600,"title":[["Can you apply lessons from other fields to this? "]]},{"children":[],"uri":"https://www.notion.so/efca32520b0647fb8ade4d8d8975175d","type":"text","createdTime":1573989039600,"lastEditedTime":1573989039600,"title":[["What mental models is this based on?"]]},{"children":[],"uri":"https://www.notion.so/8dadda1694d0405d9b0796b21fc81cd7","type":"text","createdTime":1573989039600,"lastEditedTime":1573989039600,"title":[["What other mental models might be useful for this? "]]},{"children":[],"uri":"https://www.notion.so/fad6125b270448aa94ab35e70ed7c2d0","type":"text","createdTime":1573989039600,"lastEditedTime":1573989039600,"title":[["Has someone else done or tried this? How did they do it? What can you learn from them?"]]},{"children":[],"uri":"https://www.notion.so/23e501d3e36e4c05871264c6d3b1c99e","type":"text","createdTime":1573989039600,"lastEditedTime":1573989039600,"title":[["What is something that’s unlikely anyone has tried? "]]},{"children":[],"uri":"https://www.notion.so/a9500c4cd0934339915c75cbc548f2b0","type":"text","createdTime":1573989039600,"lastEditedTime":1573989039600,"title":[["Is this a defensive or an attacking strategy? Is it to not-to-lose or to win? "]]},{"children":[],"uri":"https://www.notion.so/6d7c040aa58640b8b1d0c525ee860767","type":"text","createdTime":1573989039600,"lastEditedTime":1573989039600,"title":[["What can you experiment with?"]]},{"children":[],"uri":"https://www.notion.so/f1c28fbb833444e38a2589a0d56f54d5","type":"text","createdTime":1573989039600,"lastEditedTime":1573989039600,"title":[["What tools can you use? What tools can you create? "]]},{"children":[],"uri":"https://www.notion.so/4d069f06f21c488d84bc3c65990580c1","type":"text","createdTime":1573989039600,"lastEditedTime":1573989039600,"title":[["How can other people help you? "]]},{"children":[],"uri":"https://www.notion.so/189b1bdec6094f3dbbd6e23bf05b2c24","type":"text","createdTime":1573989039600,"lastEditedTime":1573989039600,"title":[["What constraints do you have and how can you use them to your advantage? What can you innovate with the constraints?"]]},{"children":[],"uri":"https://www.notion.so/0c0150e307ce41e1bf85d489471c0ec2","type":"text","createdTime":1573989039600,"lastEditedTime":1573989039600,"title":[]},{"children":[],"uri":"https://www.notion.so/da4671c8cfed412f81b8379576690b11","type":"text","createdTime":1573989039600,"lastEditedTime":1573989039600,"title":[]},{"children":[],"uri":"https://www.notion.so/db4daaa4cb024be0abdabf3eab02986a","type":"text","createdTime":1573989039600,"lastEditedTime":1573989039600,"title":[]},{"children":[],"uri":"https://www.notion.so/996cb903dc3a4fb58b17be1e5791f283","type":"heading","createdTime":1573989039600,"lastEditedTime":1573989039600,"title":[["Generating Thiel Answers",[["b",null],["a","https://www.syscreativity.com/all_posts.html"]]]],"depth":1},{"children":[],"uri":"https://www.notion.so/def686e1171b4f5c9f53945cbfd283f5","type":"text","createdTime":1573989039600,"lastEditedTime":1573989039600,"title":[["The Thiel Question — what is a truth very few people agree with you on — is a fantastic descriptor of contrarian truth, and a terrible generator. Here are some generators for the next time Thiel appears out of nowhere to stump you:"]]},{"children":[],"uri":"https://www.notion.so/3eda27da74d5413faf0a71db3a558b2e","type":"numbered_list","createdTime":1573989039600,"lastEditedTime":1573989039600,"title":[["What about the world is broken that no one knows is broken?"]]},{"children":[],"uri":"https://www.notion.so/c04c1bbdc4b0409b88bf01a3dbb27460","type":"numbered_list","createdTime":1573989039600,"lastEditedTime":1573989039600,"title":[["What do most people get wrong about everything?"]]},{"children":[],"uri":"https://www.notion.so/5266634a582c4f8494b8c90f0d62a693","type":"numbered_list","createdTime":1573989039600,"lastEditedTime":1573989039600,"title":[["What massive societal change is coming that no one knows is coming?"]]},{"children":[],"uri":"https://www.notion.so/3cae9196b718403ca759888deeef4dfc","type":"numbered_list","createdTime":1573989039600,"lastEditedTime":1573989039600,"title":[["What massive technological change is coming that no one knows is coming?"]]},{"children":[],"uri":"https://www.notion.so/9633fb44ec2749b5b13e3283ffa5062c","type":"numbered_list","createdTime":1573989039600,"lastEditedTime":1573989039600,"title":[["What has been fundamentally misunderstood?"]]},{"children":[],"uri":"https://www.notion.so/09b9f19de5504587becc2992c614fb28","type":"numbered_list","createdTime":1573989039600,"lastEditedTime":1573989039600,"title":[["What truths are too terrifying for us to admit?"]]},{"children":[],"uri":"https://www.notion.so/6ea6f18f49614038bd8f17b27d94802e","type":"numbered_list","createdTime":1573989039600,"lastEditedTime":1573989039600,"title":[["What do you do that you wish everyone did?"]]},{"children":[],"uri":"https://www.notion.so/9867d9966f534c9b8691156b459911bd","type":"numbered_list","createdTime":1573989039600,"lastEditedTime":1573989039600,"title":[["What supposedly implausible scenarios are actually possible, or fairly likely?"]]},{"children":[],"uri":"https://www.notion.so/941550ce78e84b79b380e4b0b56157c9","type":"numbered_list","createdTime":1573989039600,"lastEditedTime":1573989039600,"title":[["What dystopian future must actually be guarded against?"]]},{"children":[],"uri":"https://www.notion.so/b4c558579a3047eb956336b3d21a056f","type":"numbered_list","createdTime":1573989039600,"lastEditedTime":1573989039600,"title":[["What halcyon future may be possible to build?"]]},{"children":[],"uri":"https://www.notion.so/6a9d1429dc69404d985fbd472f25801b","type":"heading","createdTime":1573989039600,"lastEditedTime":1573989039600,"title":[["Lifechange Leading Questions",[["b",null],["a","https://www.syscreativity.com/all_posts.html"]]]],"depth":1},{"children":[],"uri":"https://www.notion.so/71f4b4065b4e4ee69f8e214a769da733","type":"text","createdTime":1573989039600,"lastEditedTime":1573989039600,"title":[["What we call learning is a pale imitation of generation. Knowing a thing is different from being able to do the thing — though the best way to know a thing is often to do it."]]},{"children":[],"uri":"https://www.notion.so/17adecc7e1de4ed3a33acf2a2172fb37","type":"text","createdTime":1573989039600,"lastEditedTime":1573989039600,"title":[["Creativity is best applied to relevant problems in your life. One way to bring these to mind, and which can later operate as raw material to run systematizing creativity on, is to ask leading questions. Use all, some, or none:"]]},{"children":[],"uri":"https://www.notion.so/3487eb1d2fc24476b0ce1a6b04356ff4","type":"numbered_list","createdTime":1573989039600,"lastEditedTime":1573989039600,"title":[["What do you want to change in life?"]]},{"children":[],"uri":"https://www.notion.so/b8101d853d834eb487420d9af5f4505d","type":"numbered_list","createdTime":1573989039600,"lastEditedTime":1573989039600,"title":[["What do you wish was different in your life?"]]},{"children":[],"uri":"https://www.notion.so/12530d600f3f442c8d3e357b896db431","type":"numbered_list","createdTime":1573989039600,"lastEditedTime":1573989039600,"title":[["What do you always wish you could do?"]]},{"children":[],"uri":"https://www.notion.so/98418c2b989449efa0f2bf7b71d31041","type":"numbered_list","createdTime":1573989039600,"lastEditedTime":1573989039600,"title":[["What do you think you could never do, but would want to?"]]},{"children":[],"uri":"https://www.notion.so/2d922edf30954f8fa72ab4ca5c33c8d8","type":"numbered_list","createdTime":1573989039600,"lastEditedTime":1573989039600,"title":[["What would your friends tell you to do?"]]},{"children":[],"uri":"https://www.notion.so/9a281d14c2e64f249173c5e82aa0332d","type":"numbered_list","createdTime":1573989039600,"lastEditedTime":1573989039600,"title":[["What scares you?"]]},{"children":[],"uri":"https://www.notion.so/8f042b3856a64e649f2673e04eae3ccd","type":"numbered_list","createdTime":1573989039600,"lastEditedTime":1573989039600,"title":[["What frustrates you?"]]},{"children":[],"uri":"https://www.notion.so/6b0449afbe02424786b980be4c1b4f01","type":"numbered_list","createdTime":1573989039600,"lastEditedTime":1573989039600,"title":[["What confuses you?"]]},{"children":[],"uri":"https://www.notion.so/659319bc02b74a1f8e3ee4d92b6154cd","type":"numbered_list","createdTime":1573989039600,"lastEditedTime":1573989039600,"title":[["What interests you?"]]},{"children":[],"uri":"https://www.notion.so/b2ced868b8e84ee8a2b09d85ec246a1f","type":"numbered_list","createdTime":1573989039600,"lastEditedTime":1573989039600,"title":[["What questions are you grappling with right now?"]]},{"children":[],"uri":"https://www.notion.so/21fc5f2ea4204ed4bbff8a9784ae070f","type":"numbered_list","createdTime":1573989039600,"lastEditedTime":1573989039600,"title":[["What do most people get wrong?"]]},{"children":[],"uri":"https://www.notion.so/cad2a133e7ab464684c58ff15389bd17","type":"numbered_list","createdTime":1573989039600,"lastEditedTime":1573989039600,"title":[["What do most people get wrong about everything?"]]},{"children":[],"uri":"https://www.notion.so/719978de4f244804979dca15cf16c4dc","type":"numbered_list","createdTime":1573989039600,"lastEditedTime":1573989039600,"title":[["What does your personal hell look like?"]]},{"children":[],"uri":"https://www.notion.so/db3bdcb76a824db3bab31e59c76abb26","type":"numbered_list","createdTime":1573989039600,"lastEditedTime":1573989039600,"title":[["What does your personal heaven look like?"]]},{"children":[],"uri":"https://www.notion.so/e97ded49c88f42cf817f884b3dad1efd","type":"numbered_list","createdTime":1573989039600,"lastEditedTime":1573989039600,"title":[["If you had a week to change you life before it became set in stone, what would you do? What would you focus on?"]]},{"children":[],"uri":"https://www.notion.so/138402cf6ebc48788146ca42feb58ab7","type":"numbered_list","createdTime":1573989039600,"lastEditedTime":1573989039600,"title":[["If you had 10 years to get your life in order, what would you do?"]]},{"children":[],"uri":"https://www.notion.so/7dcf7d9f1c6342d19e3f6b9d14ee6dee","type":"numbered_list","createdTime":1573989039600,"lastEditedTime":1573989039600,"title":[["If you have 10 assistants, what would you have them do for you?"]]},{"children":[],"uri":"https://www.notion.so/2d947f4f9ed64969babf54f3751271d1","type":"numbered_list","createdTime":1573989039600,"lastEditedTime":1573989039600,"title":[["If you could change 1 thing about your life, what would it be?"]]},{"children":[],"uri":"https://www.notion.so/7489bce7c3a446f58fdfba3e067a483f","type":"numbered_list","createdTime":1573989039600,"lastEditedTime":1573989039600,"title":[["If you could only improve your life an hour a day, what would you do?"]]},{"children":[],"uri":"https://www.notion.so/5fbc3071a820490ca163ff5f6b4df8d3","type":"numbered_list","createdTime":1573989039600,"lastEditedTime":1573989039600,"title":[["What do you wish everyone did?"]]},{"children":[],"uri":"https://www.notion.so/f6355fc5d7324017b2bc68f138132261","type":"numbered_list","createdTime":1573989039600,"lastEditedTime":1573989039600,"title":[["What is the truth you are too scared to admit?"]]},{"children":[],"uri":"https://www.notion.so/6ecf7099d605438998ccbc6e75cda35f","type":"numbered_list","createdTime":1573989039600,"lastEditedTime":1573989039600,"title":[["What is the truth you wish you had courage to admit?"]]},{"children":[],"uri":"https://www.notion.so/86195d111fcc4ed9ae8a05f57a15524d","type":"numbered_list","createdTime":1573989039600,"lastEditedTime":1573989039600,"title":[["If you could understand 1 thing, what would it be"]]},{"children":[],"uri":"https://www.notion.so/9c3d337695d74d449106b18f770696cd","type":"numbered_list","createdTime":1573989039600,"lastEditedTime":1573989039600,"title":[["What are the 10 academic fields you want to understand"]]},{"children":[],"uri":"https://www.notion.so/451b17abc97543709172511766996d2d","type":"numbered_list","createdTime":1573989039600,"lastEditedTime":1573989039600,"title":[["What are the tools or technologies you use to improve your life, why do you do so? What are you trying to solve?"]]},{"children":[],"uri":"https://www.notion.so/31eb4533a4694ff8b9ad90e0c6fbbeff","type":"numbered_list","createdTime":1573989039600,"lastEditedTime":1573989039600,"title":[["What do your friends say about your desires?"]]},{"children":[],"uri":"https://www.notion.so/59c3cd71c7c04d1dadfd98cbc1842ba3","type":"numbered_list","createdTime":1573989039600,"lastEditedTime":1573989039600,"title":[["What did you get most mad at yourself this week about? This quarter? The last 10 years?"]]},{"children":[],"uri":"https://www.notion.so/03cb1590df0a49e7bbbf084b8a75175c","type":"numbered_list","createdTime":1573989039600,"lastEditedTime":1573989039600,"title":[["What were you most proud of this week? This quarter? The last 10 years?"]]},{"children":[],"uri":"https://www.notion.so/588c064479504057805bcbb3bef1c488","type":"numbered_list","createdTime":1573989039600,"lastEditedTime":1573989039600,"title":[["If systematizing creativity went better than your wildest expectations, what happened? What did you focus on?"]]},{"children":[],"uri":"https://www.notion.so/6226c691efe94e5bac503df1157e766c","type":"numbered_list","createdTime":1573989039600,"lastEditedTime":1573989039600,"title":[["Create a prompt list of words, concepts, domains, people and ask is there anything you want to adopt, think about, become, take, steal, or use?"]]},{"children":[],"uri":"https://www.notion.so/51fdc68fb08d473b92b066c80518815d","type":"text","createdTime":1573989039600,"lastEditedTime":1573989039600,"title":[]},{"children":[],"uri":"https://www.notion.so/649d20d9261b4244be09343b4f114b3b","type":"text","createdTime":1573989039600,"lastEditedTime":1573989039600,"title":[]},{"children":[],"uri":"https://www.notion.so/85114b63cccf4f8294ffe7b9233b8d3e","type":"heading","createdTime":1573989039600,"lastEditedTime":1573989039600,"title":[["Compounding Knowledge Questions"]],"depth":2},{"children":[],"uri":"https://www.notion.so/a71dbef706f14a40b4240753896ca590","type":"text","createdTime":1573989039600,"lastEditedTime":1573989039600,"title":[]},{"children":[],"uri":"https://www.notion.so/8f872e811a884d33a7fdb636ec240a83","type":"bulleted_list","createdTime":1573989039600,"lastEditedTime":1573989039600,"title":[["Will you care about what your reading in a month? In a year? In five years?"]]},{"children":[],"uri":"https://www.notion.so/373c51f09d75470bbd8a2ca776ee247d","type":"bulleted_list","createdTime":1573989039600,"lastEditedTime":1573989039600,"title":[["Are you focused enough on the same thing to build cumulative knowledge or are you too spread out?"]]},{"children":[],"uri":"https://www.notion.so/4c5ece51e93f46b08dbc72b8a8b4fd4a","type":"bulleted_list","createdTime":1573989039600,"lastEditedTime":1573989039600,"title":[["What do you spend time on that’s likely to change in the next few years? What’s not likely to change?"]]},{"children":[],"uri":"https://www.notion.so/66df514f50e94422aba00057b3a13562","type":"divider","createdTime":1573989039600,"lastEditedTime":1573989039600},{"children":[],"uri":"https://www.notion.so/5be7bc28b67343f2967e0a70c50746f3","type":"text","createdTime":1573989039600,"lastEditedTime":1573989039600,"title":[]},{"children":[],"uri":"https://www.notion.so/8e63258a0b3148618688b7a2b3538354","type":"text","createdTime":1573989039600,"lastEditedTime":1573989039600,"title":[]},{"children":[],"uri":"https://www.notion.so/0be1431eb11b425f83125890a4c90235","type":"bulleted_list","createdTime":1573989039600,"lastEditedTime":1573989039600,"title":[["What are you interested in and what are you working on?"]]},{"children":[],"uri":"https://www.notion.so/e86b8ac794be44f883d2dcfd6feaf7ca","type":"bulleted_list","createdTime":1573989039600,"lastEditedTime":1573989039600,"title":[["What have you done so far that shows your potential for greatness, adjusted for whatever life circumstances you were born into?"]]},{"children":[],"uri":"https://www.notion.so/86d2f43f5990486c9061859b33159ee8","type":"bulleted_list","createdTime":1573989039600,"lastEditedTime":1573989039600,"title":[["In a best-case scenario, what do you want your obituary to say?"]]},{"children":[],"uri":"https://www.notion.so/1f11a0c225d940cc95230fbb92f2f39c","type":"text","createdTime":1573989039600,"lastEditedTime":1573989039600,"title":[]}],"uri":"https://www.notion.so/69aba3c223574e84bdedd1406149b598","type":"page","createdTime":1573989039598,"lastEditedTime":1587516480000,"title":[["問題銀行"]],"icon":"❓","fullWidth":false,"coverPosition":1,"properties":{"!`\"w":[["Yes"]],"'2]%":[["questions"]],"98uZ":[["累積的有趣問題"]],":H`m":[["Yes"]],"C'lP":[["Yes"]],"xY$N":[["‣",[["d",{"type":"date","start_date":"2020-03-30"}]]]],"{iD?":[["collection"]],"|Ay0":[["post"]],"title":[["問題銀行"]]}}